__main__.py
mcp_s3.py
mcp_s3-1.1.0.dist-info/METADATA
mcp_s3-1.1.0.dist-info/WHEEL
mcp_s3-1.1.0.dist-info/entry_points.txt
mcp_s3-1.1.0.dist-info/licenses/LICENSE
mcp_s3-1.1.0.dist-info/RECORD
