Metadata-Version: 2.4
Name: mcp-s3
Version: 1.1.0
Summary: MCP S3 File Uploader - A Model Context Protocol server for S3 uploads
Project-URL: Homepage, https://github.com/dayongd1/mcp-s3
Project-URL: Repository, https://github.com/dayongd1/mcp-s3
Project-URL: Documentation, https://github.com/dayongd1/mcp-s3/blob/main/README.md
Project-URL: Bug Tracker, https://github.com/dayongd1/mcp-s3/issues
Project-URL: Changelog, https://github.com/dayongd1/mcp-s3/releases
Author-email: Dayong Huang <dayong.d1@gmail.com>
Maintainer-email: Dayong Huang <dayong.d1@gmail.com>
License: MIT
License-File: LICENSE
Keywords: aws,fastmcp,file-upload,mcp,model-context-protocol,s3
Classifier: Development Status :: 4 - Beta
Classifier: Intended Audience :: Developers
Classifier: License :: OSI Approved :: MIT License
Classifier: Operating System :: OS Independent
Classifier: Programming Language :: Python :: 3
Classifier: Programming Language :: Python :: 3.10
Classifier: Programming Language :: Python :: 3.11
Classifier: Programming Language :: Python :: 3.12
Classifier: Topic :: Internet :: WWW/HTTP :: HTTP Servers
Classifier: Topic :: Software Development :: Libraries :: Python Modules
Classifier: Topic :: System :: Archiving :: Backup
Requires-Python: >=3.10
Requires-Dist: boto3>=1.26.0
Requires-Dist: fastmcp>=2.11.0
Requires-Dist: pydantic>=2.11.0
Requires-Dist: python-dotenv>=1.1.0
